examples/__init__.py
examples/aeolian_arp.py
examples/arpeggiator_demo.py
examples/audio_file_demo.py
examples/haunting_envelopes.py
examples/hello_world.py
examples/micro_rhythm_demo.py
examples/reverb_trem.py
examples/reverberation_demo.py
examples/sequencer_demo.py
examples/synthesizer_demo.py
examples/tempo_aware_effects.py
klang/__init__.py
klang/arpeggiator.py
klang/block.py
klang/clock.py
klang/composite.py
klang/config.py
klang/connections.py
klang/constants.py
klang/errors.py
klang/execution.py
klang/graph.py
klang/keyboard.py
klang/klang.py
klang/math.py
klang/messages.py
klang/midi.py
klang/network.py
klang/note_effects.py
klang/plotting.py
klang/primes.py
klang/progress_bar.py
klang/ring_buffer.py
klang/scraping.py
klang/sequencer.py
klang/util.py
klang/audio/__init__.py
klang/audio/_envelope.c
klang/audio/_envelope.cpython-37m-darwin.so
klang/audio/_filters.c
klang/audio/_filters.cpython-37m-darwin.so
klang/audio/effects.py
klang/audio/envelope.py
klang/audio/envelopes.py
klang/audio/filters.py
klang/audio/helpers.py
klang/audio/klanggeber.py
klang/audio/mixer.py
klang/audio/oscillators.py
klang/audio/panning.py
klang/audio/sampling.py
klang/audio/sync.py
klang/audio/synthesizer.py
klang/audio/voices.py
klang/audio/waves.py
klang/audio/wavfile.py
klang/audio/samples/gong.wav
klang/music/__init__.py
klang/music/chords.py
klang/music/intervals.py
klang/music/metre.py
klang/music/note_formatting.py
klang/music/note_values.py
klang/music/pitch.py
klang/music/rhythm.py
klang/music/scales.py
klang/music/tempo.py
klang/music/tunings.py
klang/music/data/chords.csv
klang/music/data/intervals.csv
klang/music/data/scales.csv
klang/music/data/tunings.csv
tests/__init__.py
tests/test_arpeggiator.py
tests/test_audio.py
tests/test_audio__envelope.py
tests/test_audio_envelope.py
tests/test_audio_files.py
tests/test_audio_filters.py
tests/test_audio_mixer.py
tests/test_audio_oscillators.py
tests/test_audio_sampling.py
tests/test_audio_synthesizer.py
klang-0.2.1.dist-info/METADATA
klang-0.2.1.dist-info/WHEEL
klang-0.2.1.dist-info/top_level.txt
klang-0.2.1.dist-info/RECORD
